vapy/DataSpace.py
vapy/__init__.py
vapy/covariance.py
vapy/mean_functions.py
vapy/probability.py
vapy/synth_data.py
vapy-0.0.15.dist-info/LICENSE
vapy-0.0.15.dist-info/METADATA
vapy-0.0.15.dist-info/WHEEL
vapy-0.0.15.dist-info/top_level.txt
vapy-0.0.15.dist-info/RECORD
