Metadata-Version: 2.1
Name: vapy
Version: 0.0.15
Summary: Coming soon!
Home-page: https://github.com/smonadjemi/vapy.git
Author: Shayan Monadjemi
Author-email: shayan.monadjemi@gmail.com
License: UNKNOWN
Platform: UNKNOWN
Classifier: Programming Language :: Python :: 3
Classifier: License :: OSI Approved :: MIT License
Classifier: Operating System :: OS Independent
